mscale/__init__.py
mscale/activations.py
mscale/example.py
mscale/layers.py
mscale/mscalev5.py
mscale-0.0.4.dist-info/LICENSE
mscale-0.0.4.dist-info/METADATA
mscale-0.0.4.dist-info/WHEEL
mscale-0.0.4.dist-info/top_level.txt
mscale-0.0.4.dist-info/RECORD
