Metadata-Version: 2.1
Name: mscale
Version: 0.0.4
Summary: multi-scale neural network layers
Home-page: https://gitlab.com/SpaceTimeKhantinuum/mscale
Author: Sebastian Khan
Author-email: sebastiank17@gmail.com
License: UNKNOWN
Project-URL: Bug Tracker, https://gitlab.com/SpaceTimeKhantinuum/mscale/issues
Platform: UNKNOWN
Classifier: Programming Language :: Python :: 3
Requires-Python: >=3.6
License-File: LICENSE
